ms_sdk/__init__.py
ms_sdk/ms_sdk.py
ms_sdk/Entities/Address.py
ms_sdk/Entities/Attribute.py
ms_sdk/Entities/AttributeDisplayType.py
ms_sdk/Entities/AttributeGroup.py
ms_sdk/Entities/AttributeGroupsEntities.py
ms_sdk/Entities/AttributeType.py
ms_sdk/Entities/AttributeValue.py
ms_sdk/Entities/Brand.py
ms_sdk/Entities/CatalogItem.py
ms_sdk/Entities/Company.py
ms_sdk/Entities/Currency.py
ms_sdk/Entities/CurrencyRate.py
ms_sdk/Entities/DeliveryProvider.py
ms_sdk/Entities/Document.py
ms_sdk/Entities/Entity.py
ms_sdk/Entities/EntityAttribute.py
ms_sdk/Entities/EntityAttributeValue.py
ms_sdk/Entities/Event.py
ms_sdk/Entities/FunctionalName.py
ms_sdk/Entities/Invoice.py
ms_sdk/Entities/Media.py
ms_sdk/Entities/MediaType.py
ms_sdk/Entities/Message.py
ms_sdk/Entities/Option.py
ms_sdk/Entities/Order.py
ms_sdk/Entities/OrderItem.py
ms_sdk/Entities/PaymentMethod.py
ms_sdk/Entities/PaymentProvider.py
ms_sdk/Entities/Product.py
ms_sdk/Entities/SMEntity.py
ms_sdk/Entities/Trigger.py
ms_sdk/Entities/User.py
ms_sdk/Entities/UserEvent.py
ms_sdk/Entities/Vat.py
ms_sdk/Entities/WishListItem.py
ms_sdk/Entities/__init__.py
ms_sdk/Entities/Price/ProductPriceConfiguration.py
ms_sdk/Entities/Price/__init__.py
ms_sdk/Exceptions/ConfigurationException.py
ms_sdk/Exceptions/EntityNotFoundException.py
ms_sdk/Exceptions/MethodNotFoundException.py
ms_sdk/Exceptions/SMSDKException.py
ms_sdk/Exceptions/__init__.py
ms_sdk/Lib/Collection.py
ms_sdk/Lib/ServiceInjector.py
ms_sdk/Lib/__init__.py
ms_sdk/Lib/Filters/Filter.py
ms_sdk/Lib/Filters/FilterConditions.py
ms_sdk/Lib/Filters/FilterOperators.py
ms_sdk/Lib/Filters/__init__.py
ms_sdk/Lib/Filters/Grid/AttributeFilter.py
ms_sdk/Lib/Filters/Grid/BrandFilter.py
ms_sdk/Lib/Filters/Grid/EntityFilter.py
ms_sdk/Lib/Filters/Grid/FactorFilter.py
ms_sdk/Lib/Filters/Grid/FunctionalNameFilter.py
ms_sdk/Lib/Filters/Grid/GridFilter.py
ms_sdk/Lib/Filters/Grid/GridFilterElement.py
ms_sdk/Lib/Filters/Grid/PriceRangeFilter.py
ms_sdk/Lib/Filters/Grid/__init__.py
Python_MS_SDK-0.9.dist-info/METADATA
Python_MS_SDK-0.9.dist-info/WHEEL
Python_MS_SDK-0.9.dist-info/top_level.txt
Python_MS_SDK-0.9.dist-info/RECORD
